pyfjh/__init__.py
pyfjh/atom.py
pyfjh/combo.py
pyfjh/math.py
pyfjh/stat.py
pyfjh/utli_sql.py
wfz_fjh/__init__.py
wfz_fjh/atom.py
wfz_fjh/combo.py
wfz_fjh/math.py
wfz_fjh/stat.py
wfz_fjh/utli_sql.py
wfz_fjh-1.0.4.dist-info/METADATA
wfz_fjh-1.0.4.dist-info/WHEEL
wfz_fjh-1.0.4.dist-info/top_level.txt
wfz_fjh-1.0.4.dist-info/RECORD
