Metadata-Version: 2.1
Name: wfz-fjh
Version: 1.0.4
Summary: reshape data type in py language 
Home-page: http://www.reshapedata.com
Author: fjh
Author-email: 1160230887@qq.com
License: Apache License
Keywords: reshapedata,rdt,wfz_fjh
Platform: UNKNOWN
Requires-Python: >=3.6
Requires-Dist: requests
